MANIFEST.in
README.md
requirements.txt
setup.py
vivarium_cobra/__init__.py
vivarium_cobra.egg-info/PKG-INFO
vivarium_cobra.egg-info/SOURCES.txt
vivarium_cobra.egg-info/dependency_links.txt
vivarium_cobra.egg-info/entry_points.txt
vivarium_cobra.egg-info/requires.txt
vivarium_cobra.egg-info/top_level.txt
vivarium_cobra/bigg_models/__init__.py
vivarium_cobra/bigg_models/e_coli_core.json
vivarium_cobra/bigg_models/iAF1260b.json
vivarium_cobra/composites/__init__.py
vivarium_cobra/composites/cobra_composite.py
vivarium_cobra/library/__init__.py
vivarium_cobra/library/cobra_wrapper.py
vivarium_cobra/library/lattice_utils.py
vivarium_cobra/library/regulation_logic.py
vivarium_cobra/processes/__init__.py
vivarium_cobra/processes/cobra_fba.py
vivarium_cobra/processes/configurations.py
vivarium_cobra/processes/local_field.py
vivarium_cobra/processes/volume.py