Metadata-Version: 2.1
Name: vivarium-cobra
Version: 0.0.10
Summary: UNKNOWN
Home-page: https://github.com/vivarium-collective/vivarium-cobra
Author: Eran Agmon
Author-email: eagmon@stanford.edu
License: MIT
Platform: UNKNOWN
